[{"map_name":"new_map","map_id":"x56e1KMoUddv","map_description":"\nLast Modified Thu Feb 09 2023 18:31:58 GMT+0100 (CET)","homepage":"https://escher.github.io","schema":"https://escher.github.io/escher/jsonschema/1-0-0#"},{"reactions":{"1577568":{"name":"glucose for heart cell exchange","bigg_id":"EX_glucose_h_e","reversibility":true,"label_x":1995.497802734375,"label_y":1792.419921875,"gene_reaction_rule":"","genes":[],"metabolites":[{"bigg_id":"glucose_h_e","coefficient":-1}],"segments":{"577":{"from_node_id":"1577178","to_node_id":"1577179","b1":null,"b2":null},"578":{"from_node_id":"1577180","to_node_id":"1577179","b1":null,"b2":null},"579":{"from_node_id":"1577178","to_node_id":"1577177","b1":{"x":2107.497802734375,"y":1832.419921875},"b2":{"x":2161.747802734375,"y":1832.419921875}}}},"1577569":{"name":"glucose for heart cell transport","bigg_id":"GlcHT","reversibility":true,"label_x":2345.497802734375,"label_y":1792.419921875,"gene_reaction_rule":"","genes":[],"metabolites":[{"bigg_id":"glucose_h_c","coefficient":1},{"bigg_id":"glucose_h_e","coefficient":-1}],"segments":{"580":{"from_node_id":"1577182","to_node_id":"1577183","b1":null,"b2":null},"581":{"from_node_id":"1577184","to_node_id":"1577183","b1":null,"b2":null},"582":{"from_node_id":"1577184","to_node_id":"1577185","b1":{"x":2457.497802734375,"y":1832.419921875},"b2":{"x":2511.747802734375,"y":1832.419921875}},"583":{"from_node_id":"1577182","to_node_id":"1577181","b1":{"x":2333.497802734375,"y":1832.419921875},"b2":{"x":2279.247802734375,"y":1832.419921875}}}},"1577571":{"name":"glucose for lung cell exchange","bigg_id":"EX_glucose_l_e","reversibility":true,"label_x":1990.41650390625,"label_y":1947.3994140625,"gene_reaction_rule":"","genes":[],"metabolites":[{"bigg_id":"glucose_l_e","coefficient":-1}],"segments":{"587":{"from_node_id":"1577190","to_node_id":"1577191","b1":null,"b2":null},"588":{"from_node_id":"1577192","to_node_id":"1577191","b1":null,"b2":null},"589":{"from_node_id":"1577190","to_node_id":"1577189","b1":{"x":2102.41650390625,"y":1987.3994140625},"b2":{"x":2156.66650390625,"y":1987.3994140625}}}},"1577572":{"name":"glucose for lung cell transport","bigg_id":"GlcLT","reversibility":true,"label_x":2340.41650390625,"label_y":1947.3994140625,"gene_reaction_rule":"","genes":[],"metabolites":[{"bigg_id":"glucose_l_c","coefficient":1},{"bigg_id":"glucose_l_e","coefficient":-1}],"segments":{"590":{"from_node_id":"1577194","to_node_id":"1577195","b1":null,"b2":null},"591":{"from_node_id":"1577196","to_node_id":"1577195","b1":null,"b2":null},"592":{"from_node_id":"1577196","to_node_id":"1577197","b1":{"x":2452.41650390625,"y":1987.3994140625},"b2":{"x":2506.66650390625,"y":1987.3994140625}},"593":{"from_node_id":"1577194","to_node_id":"1577193","b1":{"x":2328.41650390625,"y":1987.3994140625},"b2":{"x":2274.16650390625,"y":1987.3994140625}}}},"1577574":{"name":"glucose to by-product in heart cell","bigg_id":"GlcTBPH","reversibility":true,"label_x":2585.497802734375,"label_y":1728.3955078125,"gene_reaction_rule":"","genes":[],"metabolites":[{"bigg_id":"by_product_h_c","coefficient":1},{"bigg_id":"glucose_h_c","coefficient":-1}],"segments":{"597":{"from_node_id":"1577201","to_node_id":"1577202","b1":null,"b2":null},"598":{"from_node_id":"1577203","to_node_id":"1577202","b1":null,"b2":null},"599":{"from_node_id":"1577203","to_node_id":"1577204","b1":{"x":2570.497802734375,"y":1636.0703125},"b2":{"x":2570.497802734375,"y":1660.5804443359375}},"600":{"from_node_id":"1577201","to_node_id":"1577185","b1":{"x":2570.497802734375,"y":1798.1800537109375},"b2":{"x":2570.497802734375,"y":1773.669921875}}}},"1577576":{"name":"glucose to by-product in lung cell","bigg_id":"GlcTBPL","reversibility":true,"label_x":2582.957275390625,"label_y":2116.505126953125,"gene_reaction_rule":"","genes":[],"metabolites":[{"bigg_id":"by_product_l_c","coefficient":1},{"bigg_id":"glucose_l_c","coefficient":-1}],"segments":{"604":{"from_node_id":"1577208","to_node_id":"1577209","b1":null,"b2":null},"605":{"from_node_id":"1577210","to_node_id":"1577209","b1":null,"b2":null},"606":{"from_node_id":"1577210","to_node_id":"1577211","b1":{"x":2567.95703125,"y":2178.667724609375},"b2":{"x":2567.95703125,"y":2159.239013671875}},"607":{"from_node_id":"1577208","to_node_id":"1577197","b1":{"x":2565.41650390625,"y":2034.342529296875},"b2":{"x":2565.41650390625,"y":2046.1494140625}}}},"1577578":{"name":"By-product degradation in heart cell","bigg_id":"ByproHde","reversibility":false,"label_x":2695.497802734375,"label_y":1561.8304443359375,"gene_reaction_rule":"","genes":[],"metabolites":[{"bigg_id":"by_product_h_c","coefficient":-1}],"segments":{"611":{"from_node_id":"1577215","to_node_id":"1577216","b1":null,"b2":null},"612":{"from_node_id":"1577217","to_node_id":"1577216","b1":null,"b2":null},"613":{"from_node_id":"1577215","to_node_id":"1577204","b1":{"x":2683.497802734375,"y":1601.8304443359375},"b2":{"x":2629.247802734375,"y":1601.8304443359375}}}},"1577579":{"name":"By-product degradation in lung cell","bigg_id":"ByproLde","reversibility":false,"label_x":2692.95703125,"label_y":2177.989013671875,"gene_reaction_rule":"","genes":[],"metabolites":[{"bigg_id":"by_product_l_c","coefficient":-1}],"segments":{"614":{"from_node_id":"1577218","to_node_id":"1577219","b1":null,"b2":null},"615":{"from_node_id":"1577220","to_node_id":"1577219","b1":null,"b2":null},"616":{"from_node_id":"1577218","to_node_id":"1577211","b1":{"x":2680.95703125,"y":2217.989013671875},"b2":{"x":2626.70703125,"y":2217.989013671875}}}},"1577580":{"name":"biomass of heart cell growth","bigg_id":"BiomassH","reversibility":false,"label_x":2695.497802734375,"label_y":1792.419921875,"gene_reaction_rule":"","genes":[],"metabolites":[{"bigg_id":"glucose_h_c","coefficient":-1.001}],"segments":{"617":{"from_node_id":"1577221","to_node_id":"1577222","b1":null,"b2":null},"618":{"from_node_id":"1577223","to_node_id":"1577222","b1":null,"b2":null},"619":{"from_node_id":"1577221","to_node_id":"1577185","b1":{"x":2683.497802734375,"y":1832.419921875},"b2":{"x":2629.247802734375,"y":1832.419921875}}}},"1577581":{"name":"biomass of lung cell growth","bigg_id":"BiomassL","reversibility":false,"label_x":2690.41650390625,"label_y":1947.3994140625,"gene_reaction_rule":"","genes":[],"metabolites":[{"bigg_id":"glucose_l_c","coefficient":-0.999}],"segments":{"620":{"from_node_id":"1577224","to_node_id":"1577225","b1":null,"b2":null},"621":{"from_node_id":"1577226","to_node_id":"1577225","b1":null,"b2":null},"622":{"from_node_id":"1577224","to_node_id":"1577197","b1":{"x":2678.41650390625,"y":1987.3994140625},"b2":{"x":2624.16650390625,"y":1987.3994140625}}}}},"nodes":{"1577177":{"node_type":"metabolite","x":2220.497802734375,"y":1832.419921875,"bigg_id":"glucose_h_e","name":"glucose_for_heart_cell","label_x":2161.097802734375,"label_y":1872.419921875,"node_is_primary":true},"1577178":{"node_type":"multimarker","x":2065.497802734375,"y":1832.419921875},"1577179":{"node_type":"midmarker","x":2045.497802734375,"y":1832.419921875},"1577180":{"node_type":"multimarker","x":2025.497802734375,"y":1832.419921875},"1577181":{"node_type":"metabolite","x":2220.497802734375,"y":1832.419921875,"bigg_id":"glucose_h_e","name":"glucose_for_heart_cell","label_x":2161.097802734375,"label_y":1872.419921875,"node_is_primary":true},"1577182":{"node_type":"multimarker","x":2375.497802734375,"y":1832.419921875},"1577183":{"node_type":"midmarker","x":2395.497802734375,"y":1832.419921875},"1577184":{"node_type":"multimarker","x":2415.497802734375,"y":1832.419921875},"1577185":{"node_type":"metabolite","x":2570.497802734375,"y":1832.419921875,"bigg_id":"glucose_h_c","name":"glucose_for_heart_cell","label_x":2508.557275390625,"label_y":1880.0418701171875,"node_is_primary":true},"1577189":{"node_type":"metabolite","x":2215.41650390625,"y":1987.3994140625,"bigg_id":"glucose_l_e","name":"glucose_for_lung_cell","label_x":2156.01650390625,"label_y":2027.3994140625,"node_is_primary":true},"1577190":{"node_type":"multimarker","x":2060.41650390625,"y":1987.3994140625},"1577191":{"node_type":"midmarker","x":2040.41650390625,"y":1987.3994140625},"1577192":{"node_type":"multimarker","x":2020.41650390625,"y":1987.3994140625},"1577193":{"node_type":"metabolite","x":2215.41650390625,"y":1987.3994140625,"bigg_id":"glucose_l_e","name":"glucose_for_lung_cell","label_x":2156.01650390625,"label_y":2027.3994140625,"node_is_primary":true},"1577194":{"node_type":"multimarker","x":2370.41650390625,"y":1987.3994140625},"1577195":{"node_type":"midmarker","x":2390.41650390625,"y":1987.3994140625},"1577196":{"node_type":"multimarker","x":2410.41650390625,"y":1987.3994140625},"1577197":{"node_type":"metabolite","x":2565.41650390625,"y":1987.3994140625,"bigg_id":"glucose_l_c","name":"glucose_for_lung_cell","label_x":2500.935205078125,"label_y":1958.802001953125,"node_is_primary":true},"1577201":{"node_type":"multimarker","x":2570.497802734375,"y":1756.1800537109375},"1577202":{"node_type":"midmarker","x":2570.497802734375,"y":1718.3955078125},"1577203":{"node_type":"multimarker","x":2570.497802734375,"y":1678.0703125},"1577204":{"node_type":"metabolite","x":2570.497802734375,"y":1601.8304443359375,"bigg_id":"by_product_h_c","name":"by_product_from_glucose_h","label_x":2369.380126953125,"label_y":1617.0743408203125,"node_is_primary":true},"1577208":{"node_type":"multimarker","x":2565.41650390625,"y":2076.342529296875},"1577209":{"node_type":"midmarker","x":2567.957275390625,"y":2106.505126953125},"1577210":{"node_type":"multimarker","x":2567.95703125,"y":2136.667724609375},"1577211":{"node_type":"metabolite","x":2567.95703125,"y":2217.989013671875,"bigg_id":"by_product_l_c","name":"by_product_from_glucose_l","label_x":2379.54248046875,"label_y":2217.989013671875,"node_is_primary":true},"1577215":{"node_type":"multimarker","x":2725.497802734375,"y":1601.8304443359375},"1577216":{"node_type":"midmarker","x":2745.497802734375,"y":1601.8304443359375},"1577217":{"node_type":"multimarker","x":2765.497802734375,"y":1601.8304443359375},"1577218":{"node_type":"multimarker","x":2722.95703125,"y":2217.989013671875},"1577219":{"node_type":"midmarker","x":2742.95703125,"y":2217.989013671875},"1577220":{"node_type":"multimarker","x":2762.95703125,"y":2217.989013671875},"1577221":{"node_type":"multimarker","x":2725.497802734375,"y":1832.419921875},"1577222":{"node_type":"midmarker","x":2745.497802734375,"y":1832.419921875},"1577223":{"node_type":"multimarker","x":2765.497802734375,"y":1832.419921875},"1577224":{"node_type":"multimarker","x":2720.41650390625,"y":1987.3994140625},"1577225":{"node_type":"midmarker","x":2740.41650390625,"y":1987.3994140625},"1577226":{"node_type":"multimarker","x":2760.41650390625,"y":1987.3994140625}},"text_labels":{"7":{"x":2944.58251953125,"y":1852.7451171875,"text":"Heart Cell"},"8":{"x":2936.960693359375,"y":2028.0498046875,"text":"Lung cell"}},"canvas":{"x":1969.5484020233155,"y":1508.1524169921875,"width":1249.5858264923097,"height":760.7565673828124}}]